tokei_pie/__init__.py
tokei_pie/colors.json
tokei_pie/main.py
tokei_pie-1.2.1.dist-info/LICENSE
tokei_pie-1.2.1.dist-info/METADATA
tokei_pie-1.2.1.dist-info/WHEEL
tokei_pie-1.2.1.dist-info/entry_points.txt
tokei_pie-1.2.1.dist-info/RECORD
